rest_framework_simplejwt_mongoengine/__init__.py
rest_framework_simplejwt_mongoengine/authentication.py
rest_framework_simplejwt_mongoengine/backends.py
rest_framework_simplejwt_mongoengine/exceptions.py
rest_framework_simplejwt_mongoengine/models.py
rest_framework_simplejwt_mongoengine/py.typed
rest_framework_simplejwt_mongoengine/serializers.py
rest_framework_simplejwt_mongoengine/settings.py
rest_framework_simplejwt_mongoengine/state.py
rest_framework_simplejwt_mongoengine/tokens.py
rest_framework_simplejwt_mongoengine/utils.py
rest_framework_simplejwt_mongoengine/views.py
rest_framework_simplejwt_mongoengine/locale/ar/LC_MESSAGES/django.mo
rest_framework_simplejwt_mongoengine/locale/ar/LC_MESSAGES/django.po
rest_framework_simplejwt_mongoengine/locale/cs/LC_MESSAGES/django.mo
rest_framework_simplejwt_mongoengine/locale/cs/LC_MESSAGES/django.po
rest_framework_simplejwt_mongoengine/locale/de/LC_MESSAGES/django.mo
rest_framework_simplejwt_mongoengine/locale/de/LC_MESSAGES/django.po
rest_framework_simplejwt_mongoengine/locale/es/LC_MESSAGES/django.mo
rest_framework_simplejwt_mongoengine/locale/es/LC_MESSAGES/django.po
rest_framework_simplejwt_mongoengine/locale/es_AR/LC_MESSAGES/django.mo
rest_framework_simplejwt_mongoengine/locale/es_AR/LC_MESSAGES/django.po
rest_framework_simplejwt_mongoengine/locale/es_CL/LC_MESSAGES/django.mo
rest_framework_simplejwt_mongoengine/locale/es_CL/LC_MESSAGES/django.po
rest_framework_simplejwt_mongoengine/locale/fa/LC_MESSAGES/django.mo
rest_framework_simplejwt_mongoengine/locale/fa/LC_MESSAGES/django.po
rest_framework_simplejwt_mongoengine/locale/fa_IR/LC_MESSAGES/django.mo
rest_framework_simplejwt_mongoengine/locale/fa_IR/LC_MESSAGES/django.po
rest_framework_simplejwt_mongoengine/locale/fr/LC_MESSAGES/django.mo
rest_framework_simplejwt_mongoengine/locale/fr/LC_MESSAGES/django.po
rest_framework_simplejwt_mongoengine/locale/he_IL/LC_MESSAGES/django.mo
rest_framework_simplejwt_mongoengine/locale/he_IL/LC_MESSAGES/django.po
djangorestframework_simplejwt_mongoengine-1.3.0.dist-info/METADATA
djangorestframework_simplejwt_mongoengine-1.3.0.dist-info/WHEEL
djangorestframework_simplejwt_mongoengine-1.3.0.dist-info/top_level.txt
djangorestframework_simplejwt_mongoengine-1.3.0.dist-info/RECORD
