Metadata-Version: 2.1
Name: djangorestframework_simplejwt_mongoengine
Version: 1.3.0
Summary: Simple JWT is a JSON Web Token authentication plugin for the Django REST Framework which to be compatible with MongoEngine.
Home-page: https://github.com/ngocngoan/djangorestframework-simplejwt-mongoengine
Author: Đỗ Ngọc Ngoạn (aka Ngoan Do)
Author-email: ngocngoan060288@gmail.com
License: GNU General Public License v3
Keywords: djangorestframework_simplejwt_mongoengine
Classifier: Development Status :: 5 - Production/Stable
Classifier: Environment :: Web Environment
Classifier: Framework :: Django
Classifier: Framework :: Django :: 3.2
Classifier: Framework :: Django :: 4.1
Classifier: Framework :: Django :: 4.2
Classifier: Intended Audience :: Developers
Classifier: License :: OSI Approved :: GNU General Public License v3 (GPLv3)
Classifier: Natural Language :: English
Classifier: Programming Language :: Python
Classifier: Programming Language :: Python :: 3
Classifier: Programming Language :: Python :: 3.8
Classifier: Programming Language :: Python :: 3.9
Classifier: Programming Language :: Python :: 3.10
Classifier: Programming Language :: Python :: 3.11
Classifier: Topic :: Internet :: WWW/HTTP
Requires-Python: >=3.8
Requires-Dist: django <4.3,>=3.2
Requires-Dist: djangorestframework >=3.12
Requires-Dist: django-mongoengine >=0.5.4
Requires-Dist: pyjwt <3,>=1.7.1
Provides-Extra: crypto
Requires-Dist: cryptography >=3.3.1 ; extra == 'crypto'
Provides-Extra: dev
Requires-Dist: pytest-watch ; extra == 'dev'
Requires-Dist: wheel ; extra == 'dev'
Requires-Dist: twine ; extra == 'dev'
Requires-Dist: ipython ; extra == 'dev'
Requires-Dist: cryptography ; extra == 'dev'
Requires-Dist: coverage ; extra == 'dev'
Requires-Dist: freezegun ; extra == 'dev'
Requires-Dist: psutil ; extra == 'dev'
Requires-Dist: python-jose ; extra == 'dev'
Requires-Dist: pytest-cov ; extra == 'dev'
Requires-Dist: pytest-django ; extra == 'dev'
Requires-Dist: pytest-xdist ; extra == 'dev'
Requires-Dist: pytest ; extra == 'dev'
Requires-Dist: tox ; extra == 'dev'
Requires-Dist: flake8 ; extra == 'dev'
Requires-Dist: pep8 ; extra == 'dev'
Requires-Dist: isort ; extra == 'dev'
Requires-Dist: Sphinx >=7 ; extra == 'dev'
Requires-Dist: sphinx-rtd-theme >=2.0.0 ; extra == 'dev'
Requires-Dist: python-jose ==3.3.0 ; extra == 'dev'
Provides-Extra: doc
Requires-Dist: Sphinx >=7 ; extra == 'doc'
Requires-Dist: sphinx-rtd-theme >=2.0.0 ; extra == 'doc'
Provides-Extra: lint
Requires-Dist: flake8 ; extra == 'lint'
Requires-Dist: pep8 ; extra == 'lint'
Requires-Dist: isort ; extra == 'lint'
Provides-Extra: python-jose
Requires-Dist: python-jose ==3.3.0 ; extra == 'python-jose'
Provides-Extra: test
Requires-Dist: cryptography ; extra == 'test'
Requires-Dist: coverage ; extra == 'test'
Requires-Dist: freezegun ; extra == 'test'
Requires-Dist: psutil ; extra == 'test'
Requires-Dist: python-jose ; extra == 'test'
Requires-Dist: pytest-cov ; extra == 'test'
Requires-Dist: pytest-django ; extra == 'test'
Requires-Dist: pytest-xdist ; extra == 'test'
Requires-Dist: pytest ; extra == 'test'
Requires-Dist: tox ; extra == 'test'
